callpyfile/LICENSE
callpyfile/README.MD
callpyfile/__init__.py
callpyfile/requirements.txt
callpyfile/thirdparty.json
callpyfile-0.10.dist-info/LICENSE.rst
callpyfile-0.10.dist-info/METADATA
callpyfile-0.10.dist-info/WHEEL
callpyfile-0.10.dist-info/top_level.txt
callpyfile-0.10.dist-info/RECORD
