Metadata-Version: 2.1
Name: callpyfile
Version: 0.10
Summary: Executes python scripts in different environments without writing temp files to disk, it can pass and receive any type of variable, multiprocessing can be executed from everywhere, not only at top-level
Home-page: https://github.com/hansalemaos/callpyfile
Author: Johannes Fischer
Author-email: <aulasparticularesdealemaosp@gmail.com>
License: MIT
Keywords: env,dill,pickle,multiprocessing,subprocess
Classifier: Development Status :: 4 - Beta
Classifier: Programming Language :: Python :: 3 :: Only
Classifier: Programming Language :: Python :: 3.9
Classifier: Topic :: Scientific/Engineering :: Visualization
Classifier: Topic :: Software Development :: Libraries :: Python Modules
Classifier: Topic :: Text Editors :: Text Processing
Classifier: Topic :: Text Processing :: General
Classifier: Topic :: Text Processing :: Indexing
Classifier: Topic :: Text Processing :: Filters
Classifier: Topic :: Utilities
License-File: LICENSE.rst
